misc/DTServices-14.2.txt
misc/DTServices-14.5.txt
misc/RemoteXPC.md
misc/plist_sniffer.py
misc/pyinstaller.md
misc/remotexpc_sniffer.py
misc/understanding_idevice_protocol_layers.md
misc/usbmux_sniff.sh
pymobiledevice3/__init__.py
pymobiledevice3/__main__.py
pymobiledevice3/_version.py
pymobiledevice3/bonjour.py
pymobiledevice3/ca.py
pymobiledevice3/common.py
pymobiledevice3/exceptions.py
pymobiledevice3/irecv.py
pymobiledevice3/irecv_devices.py
pymobiledevice3/lockdown.py
pymobiledevice3/lockdown_service_provider.py
pymobiledevice3/pair_records.py
pymobiledevice3/service_connection.py
pymobiledevice3/tcp_forwarder.py
pymobiledevice3/usbmux.py
pymobiledevice3/utils.py
pymobiledevice3/cli/__init__.py
pymobiledevice3/cli/activation.py
pymobiledevice3/cli/afc.py
pymobiledevice3/cli/amfi.py
pymobiledevice3/cli/apps.py
pymobiledevice3/cli/backup.py
pymobiledevice3/cli/bonjour.py
pymobiledevice3/cli/cli_common.py
pymobiledevice3/cli/companion_proxy.py
pymobiledevice3/cli/crash.py
pymobiledevice3/cli/idam.py
pymobiledevice3/cli/lockdown.py
pymobiledevice3/cli/mounter.py
pymobiledevice3/cli/notification.py
pymobiledevice3/cli/pcap.py
pymobiledevice3/cli/power_assertion.py
pymobiledevice3/cli/processes.py
pymobiledevice3/cli/profile.py
pymobiledevice3/cli/provision.py
pymobiledevice3/cli/remote.py
pymobiledevice3/cli/restore.py
pymobiledevice3/cli/springboard.py
pymobiledevice3/cli/syslog.py
pymobiledevice3/cli/usbmux.py
pymobiledevice3/cli/version.py
pymobiledevice3/cli/webinspector.py
pymobiledevice3/cli/developer/__init__.py
pymobiledevice3/cli/developer/arbitration.py
pymobiledevice3/cli/developer/condition.py
pymobiledevice3/cli/developer/core_device.py
pymobiledevice3/cli/developer/debugserver.py
pymobiledevice3/cli/developer/fetch_symbols.py
pymobiledevice3/cli/developer/simulate_location.py
pymobiledevice3/cli/developer/accessibility/__init__.py
pymobiledevice3/cli/developer/accessibility/settings.py
pymobiledevice3/cli/developer/dvt/__init__.py
pymobiledevice3-7.0.6.dist-info/licenses/LICENSE
pymobiledevice3-7.0.6.dist-info/METADATA
pymobiledevice3-7.0.6.dist-info/WHEEL
pymobiledevice3-7.0.6.dist-info/entry_points.txt
pymobiledevice3-7.0.6.dist-info/top_level.txt
pymobiledevice3-7.0.6.dist-info/RECORD
