Metadata-Version: 2.4
Name: pymobiledevice3
Version: 7.0.6
Summary: Pure python3 implementation for working with iDevices (iPhone, etc...)
Author-email: doronz88 <doron88@gmail.com>, matan <matan1008@gmail.com>
Maintainer-email: doronz88 <doron88@gmail.com>, matan <matan1008@gmail.com>
License-Expression: GPL-3.0-or-later
Project-URL: Homepage, https://github.com/doronz88/pymobiledevice3
Project-URL: Bug Reports, https://github.com/doronz88/pymobiledevice3/issues
Keywords: ios,protocol,lockdownd,instruments,automation,cli,afc
Classifier: Development Status :: 5 - Production/Stable
Classifier: Programming Language :: Python :: 3
Classifier: Programming Language :: Python :: 3.9
Classifier: Programming Language :: Python :: 3.10
Classifier: Programming Language :: Python :: 3.11
Classifier: Programming Language :: Python :: 3.12
Classifier: Programming Language :: Python :: 3.13
Classifier: Programming Language :: Python :: 3.14
Classifier: Programming Language :: Python :: 3 :: Only
Requires-Python: >=3.9
License-File: LICENSE
Requires-Dist: construct>=2.9.29
Requires-Dist: construct-typing>=0.7.0
Requires-Dist: asn1
Requires-Dist: coloredlogs
Requires-Dist: IPython
Requires-Dist: bpylist2>=4.0.1
Requires-Dist: pygments
Requires-Dist: hexdump
Requires-Dist: daemonize
Requires-Dist: gpxpy!=1.6.0,<1.7.0
Requires-Dist: pykdebugparser>=1.2.7
Requires-Dist: pyusb>=1.2.1
Requires-Dist: tqdm
Requires-Dist: requests
Requires-Dist: xonsh
Requires-Dist: parameter_decorators
Requires-Dist: packaging
Requires-Dist: pygnuutils>=0.0.7
Requires-Dist: cryptography>=41.0.1
Requires-Dist: pycrashreport>=1.2.7
Requires-Dist: fastapi[all]>=0.93.0
Requires-Dist: uvicorn>=0.15.0
Requires-Dist: wsproto
Requires-Dist: nest_asyncio>=1.5.5
Requires-Dist: Pillow
Requires-Dist: inquirer3>=0.6.0
Requires-Dist: ipsw_parser>=1.5.0
Requires-Dist: ifaddr
Requires-Dist: hyperframe
Requires-Dist: srptools
Requires-Dist: qh3<2,>=1.0.0
Requires-Dist: developer_disk_image>=0.0.2
Requires-Dist: opack2
Requires-Dist: psutil
Requires-Dist: pytun-pmd3>=3.0.2
Requires-Dist: prompt_toolkit
Requires-Dist: sslpsk-pmd3>=1.0.3; python_version < "3.13"
Requires-Dist: python-pcapng>=2.1.1
Requires-Dist: plumbum
Requires-Dist: pyimg4>=0.8.8
Requires-Dist: typer>=0.20.0
Requires-Dist: typer-injector>=0.2.0
Provides-Extra: test
Requires-Dist: pytest; extra == "test"
Requires-Dist: pytest-asyncio; extra == "test"
Dynamic: license-file
